autotwin_bselib/__init__.py
autotwin_bselib/ekf_core.py
autotwin_bselib/gates.py
autotwin_bselib/inspect_mat.py
autotwin_bselib/io_utils.py
autotwin_bselib/ocv.py
autotwin_bselib/pe.py
autotwin_bselib/soc_est.py
autotwin_bselib-0.1.2.dist-info/licenses/LICENSE
autotwin_bselib-0.1.2.dist-info/METADATA
autotwin_bselib-0.1.2.dist-info/WHEEL
autotwin_bselib-0.1.2.dist-info/RECORD
