Metadata-Version: 2.4
Name: autotwin_bselib
Version: 0.1.2
Summary: Battery SoC Estimation Library for Auto-Twin
License: BSD-3-Clause
License-File: LICENSE
Keywords: auto-twin,battery model,SoC estimation
Author: Yiqi Jia
Author-email: yiqi.jia@polimi.it
Requires-Python: >=3.10,<4.0
Classifier: Development Status :: 1 - Planning
Classifier: Intended Audience :: Manufacturing
Classifier: License :: OSI Approved :: BSD License
Classifier: Operating System :: OS Independent
Classifier: Programming Language :: Python :: 3
Classifier: Programming Language :: Python :: 3.10
Classifier: Programming Language :: Python :: 3.11
Classifier: Programming Language :: Python :: 3.12
Classifier: Programming Language :: Python :: 3.13
Classifier: Programming Language :: Python :: 3.14
Classifier: Programming Language :: Python :: 3 :: Only
Requires-Dist: matplotlib (>=3.10.6,<4.0.0)
Requires-Dist: neo4j (>=5.17.0,<6.0.0)
Requires-Dist: pandas (>=2.3.2,<3.0.0)
Requires-Dist: scipy (>=1.15.3,<2.0.0)
Project-URL: Homepage, https://github.com/AutotwinEU/batt-soc-est
